regrws/__init__.py
regrws/api/__init__.py
regrws/api/constants.py
regrws/api/core.py
regrws/api/manager.py
regrws/models/__init__.py
regrws/models/base.py
regrws/models/customer.py
regrws/models/error.py
regrws/models/nested.py
regrws/models/net.py
regrws/models/org.py
regrws/models/poc.py
regrws/models/tickets.py
regrws/models/types.py
regrws/settings.py
pyregrws-0.2.3.dist-info/METADATA
pyregrws-0.2.3.dist-info/WHEEL
pyregrws-0.2.3.dist-info/licenses/LICENSE
pyregrws-0.2.3.dist-info/RECORD
