Metadata-Version: 2.4
Name: pyregrws
Version: 0.2.3
Summary: Python library to retrieve and modify records within ARIN's database through their Reg-RWS service
License: Apache 2.0
License-File: LICENSE
Author: Jonathan Senecal
Author-email: contact@jonathansenecal.com
Requires-Python: >=3.11,<4.0
Classifier: Development Status :: 3 - Alpha
Classifier: Framework :: Pydantic
Classifier: Intended Audience :: Developers
Classifier: License :: OSI Approved :: Apache Software License
Classifier: License :: Other/Proprietary License
Classifier: Operating System :: OS Independent
Classifier: Programming Language :: Python :: 3
Classifier: Programming Language :: Python :: 3.11
Classifier: Programming Language :: Python :: 3.12
Classifier: Programming Language :: Python :: 3.13
Classifier: Programming Language :: Python :: 3.14
Classifier: Topic :: Internet
Classifier: Topic :: Software Development :: Libraries :: Python Modules
Requires-Dist: certifi (>=2025.0.0,<2026.0.0)
Requires-Dist: pydantic-xml (==1.0.0)
Requires-Dist: pydantic[dotenv] (>=1.10.22,<2.0.0)
Requires-Dist: requests (>=2.28.1,<3.0.0)
Project-URL: Homepage, https://github.com/jsenecal/pyregrws
